<?xml version="1.0" encoding="UTF-8" standalone="yes"?>
<AttributeSetGroup xmlns:ns2="http://www.example.org/productType">
    <resource>FFG_TIR_HIRES</resource>
    <attrSetGroupName>standard</attrSetGroupName>
    
    <attrSetLabels>
         <attrSetLabel>
              <name>ffg1224hr</name>
              <alias></alias>
         </attrSetLabel>
         <attrSetLabel>
              <name>FFG0124hr</name>
              <alias></alias>
         </attrSetLabel>
    </attrSetLabels>

</AttributeSetGroup>

